{
  "task_id": "build-blackroad-authelia",
  "title": "Build BlackRoad Auth Portal",
  "description": "SSO + 2FA with beautiful interface. Advanced security features.",
  "priority": "high",
  "tags": "auth,security",
  "skills": "fullstack",
  "status": "completed",
  "posted_at": "2026-01-09T21:09:49.3NZ",
  "posted_by": "unknown",
  "claimed_by": "unknown",
  "claimed_at": "2026-01-10T01:01:22.3NZ",
  "timeout_at": "2026-01-10T01:31:22.3NZ",
  "completed_at": "2026-01-10T01:28:26.3NZ",
  "result": "Built RoadAuth Pro - Enterprise zero-trust identity platform (Product #82). Live at https://fb365a0c.blackroad-admin.pages.dev. Features: Multi-factor auth (TOTP, WebAuthn, YubiKey), SSO (OAuth/OIDC/SAML), Zero-trust architecture, Mobile authenticator, LDAP/AD integration, Policy engine. Pricing: $99/mo Team → $299/mo Business → Custom Enterprise. 🤖 Product #82 of 200+"
}
